nestedutils/__init__.py
nestedutils/access.py
nestedutils/constants.py
nestedutils/enums.py
nestedutils/exceptions.py
nestedutils/helpers.py
nestedutils/py.typed
nestedutils-1.1.7.dist-info/METADATA
nestedutils-1.1.7.dist-info/WHEEL
nestedutils-1.1.7.dist-info/licenses/LICENSE
nestedutils-1.1.7.dist-info/RECORD
