Metadata-Version: 2.4
Name: nestedutils
Version: 1.1.7
Summary: The lightweight Python library for safe, simple, dot-notation access to nested dicts and lists. Effortlessly get, set, and delete values deep in your complex JSON, API responses, and config files without verbose error-checking or handling KeyError exceptions.
Project-URL: Homepage, https://github.com/ysskrishna/nestedutils
Project-URL: Documentation, https://ysskrishna.github.io/nestedutils/
Project-URL: Repository, https://github.com/ysskrishna/nestedutils.git
Project-URL: Issues, https://github.com/ysskrishna/nestedutils/issues
Author-email: ysskrishna <sivasaikrishnassk@gmail.com>
License: MIT
License-File: LICENSE
Keywords: KeyError,config,config-utils,data-utils,deep-access,deep-delete,deep-get,deep-set,dict,dict-utils,dictionary,dot-access,dot-notation,json,json-access,json-utils,key-error-handling,keypath,list,nested,nested-data,nested-dict,no-keyerror,path-access,safe-access,utilities,utils
Classifier: Development Status :: 5 - Production/Stable
Classifier: Intended Audience :: Developers
Classifier: License :: OSI Approved :: MIT License
Classifier: Operating System :: OS Independent
Classifier: Programming Language :: Python :: 3
Classifier: Programming Language :: Python :: 3.8
Classifier: Programming Language :: Python :: 3.9
Classifier: Programming Language :: Python :: 3.10
Classifier: Programming Language :: Python :: 3.11
Classifier: Programming Language :: Python :: 3.12
Classifier: Topic :: Software Development :: Libraries :: Python Modules
Classifier: Topic :: Utilities
Classifier: Typing :: Typed
Requires-Python: >=3.8
